{
  "name": "Git Meta CLI Testing Environment",
  "image": "ubuntu:22.04",
  "features": {
    "ghcr.io/devcontainers/features/common-utils:2": {
      "installZsh": true,
      "configureZshAsDefaultShell": true,
      "installOhMyZsh": true,
      "upgradePackages": true,
      "username": "vscode",
      "userUid": 1000,
      "userGid": 1000
    },
    "ghcr.io/devcontainers/features/git:1": {
      "ppa": true,
      "version": "latest"
    },
    "ghcr.io/devcontainers/features/node:1": {
      "nodeGypDependencies": true,
      "installYarnUsingApt": false,
      "version": "18"
    },
    "ghcr.io/devcontainers/features/python:1": {
      "version": "3.10"
    }
  },
  "postCreateCommand": "bash .devcontainer/install-tools.sh",
  "customizations": {
    "vscode": {
      "extensions": [
        "timonwong.shellcheck",
        "foxundermoon.shell-format",
        "ms-vscode.test-adapter-converter",
        "hbenl.vscode-test-explorer",
        "ms-vscode.js-debug",
        "dbaeumer.vscode-eslint",
        "esbenp.prettier-vscode",
        "rogalmic.bash-debug"
      ]
    }
  },
  "forwardPorts": [],
  "remoteUser": "vscode"
}